{
  "_class": "shapePath",
  "booleanOperation": 3,
  "do_objectID": "E32D37D9-4817-4900-B1DD-3FEE621F5E6A",
  "edited": true,
  "exportOptions": {
    "_class": "exportOptions",
    "exportFormats": [
    ],
    "includedLayerIds": [
    ],
    "layerOptions": 0,
    "shouldTrim": false
  },
  "frame": {
    "_class": "rect",
    "constrainProportions": false,
    "height": 23.994140625,
    "width": 20.478515625,
    "x": 126.939453125,
    "y": 6.005859375
  },
  "isClosed": true,
  "isFlippedHorizontal": false,
  "isFlippedVertical": false,
  "isLocked": false,
  "isVisible": true,
  "layerListExpandedType": 0,
  "name": "IHR ZUHAUSE KÜMMERT Copy",
  "nameIsFixed": false,
  "path": {
    "_class": "path",
    "isClosed": true,
    "pointRadiusBehaviour": 1,
    "points": [
      {
        "_class": "curvePoint",
        "cornerRadius": 0,
        "curveFrom": "{0.37167381974248925, 0}",
        "curveMode": 1,
        "curveTo": "{0.37167381974248925, 0}",
        "hasCurveFrom": false,
        "hasCurveTo": false,
        "point": "{0.37167381974248925, 0}"
      },
      {
        "_class": "curvePoint",
        "cornerRadius": 0,
        "curveFrom": "{0.62918454935622314, 0}",
        "curveMode": 1,
        "curveTo": "{0.62918454935622314, 0}",
        "hasCurveFrom": false,
        "hasCurveTo": false,
        "point": "{0.62918454935622314, 0}"
      },
      {
        "_class": "curvePoint",
        "cornerRadius": 0,
        "curveFrom": "{1, 1}",
        "curveMode": 1,
        "curveTo": "{1, 1}",
        "hasCurveFrom": false,
        "hasCurveTo": false,
        "point": "{1, 1}"
      },
      {
        "_class": "curvePoint",
        "cornerRadius": 0,
        "curveFrom": "{0.7381974248927039, 1}",
        "curveMode": 1,
        "curveTo": "{0.7381974248927039, 1}",
        "hasCurveFrom": false,
        "hasCurveTo": false,
        "point": "{0.7381974248927039, 1}"
      },
      {
        "_class": "curvePoint",
        "cornerRadius": 0,
        "curveFrom": "{0.66523605150214593, 0.77655677655677657}",
        "curveMode": 1,
        "curveTo": "{0.66523605150214593, 0.77655677655677657}",
        "hasCurveFrom": false,
        "hasCurveTo": false,
        "point": "{0.66523605150214593, 0.77655677655677657}"
      },
      {
        "_class": "curvePoint",
        "cornerRadius": 0,
        "curveFrom": "{0.33133047210300431, 0.77655677655677657}",
        "curveMode": 1,
        "curveTo": "{0.33133047210300431, 0.77655677655677657}",
        "hasCurveFrom": false,
        "hasCurveTo": false,
        "point": "{0.33133047210300431, 0.77655677655677657}"
      },
      {
        "_class": "curvePoint",
        "cornerRadius": 0,
        "curveFrom": "{0.25751072961373389, 1}",
        "curveMode": 1,
        "curveTo": "{0.25751072961373389, 1}",
        "hasCurveFrom": false,
        "hasCurveTo": false,
        "point": "{0.25751072961373389, 1}"
      },
      {
        "_class": "curvePoint",
        "cornerRadius": 0,
        "curveFrom": "{0, 1}",
        "curveMode": 1,
        "curveTo": "{0, 1}",
        "hasCurveFrom": false,
        "hasCurveTo": false,
        "point": "{0, 1}"
      }
    ]
  },
  "pointRadiusBehaviour": 1,
  "points": [
    {
      "_class": "curvePoint",
      "cornerRadius": 0,
      "curveFrom": "{0.37167381974248925, 0}",
      "curveMode": 1,
      "curveTo": "{0.37167381974248925, 0}",
      "hasCurveFrom": false,
      "hasCurveTo": false,
      "point": "{0.37167381974248925, 0}"
    },
    {
      "_class": "curvePoint",
      "cornerRadius": 0,
      "curveFrom": "{0.62918454935622314, 0}",
      "curveMode": 1,
      "curveTo": "{0.62918454935622314, 0}",
      "hasCurveFrom": false,
      "hasCurveTo": false,
      "point": "{0.62918454935622314, 0}"
    },
    {
      "_class": "curvePoint",
      "cornerRadius": 0,
      "curveFrom": "{1, 1}",
      "curveMode": 1,
      "curveTo": "{1, 1}",
      "hasCurveFrom": false,
      "hasCurveTo": false,
      "point": "{1, 1}"
    },
    {
      "_class": "curvePoint",
      "cornerRadius": 0,
      "curveFrom": "{0.7381974248927039, 1}",
      "curveMode": 1,
      "curveTo": "{0.7381974248927039, 1}",
      "hasCurveFrom": false,
      "hasCurveTo": false,
      "point": "{0.7381974248927039, 1}"
    },
    {
      "_class": "curvePoint",
      "cornerRadius": 0,
      "curveFrom": "{0.66523605150214593, 0.77655677655677657}",
      "curveMode": 1,
      "curveTo": "{0.66523605150214593, 0.77655677655677657}",
      "hasCurveFrom": false,
      "hasCurveTo": false,
      "point": "{0.66523605150214593, 0.77655677655677657}"
    },
    {
      "_class": "curvePoint",
      "cornerRadius": 0,
      "curveFrom": "{0.33133047210300431, 0.77655677655677657}",
      "curveMode": 1,
      "curveTo": "{0.33133047210300431, 0.77655677655677657}",
      "hasCurveFrom": false,
      "hasCurveTo": false,
      "point": "{0.33133047210300431, 0.77655677655677657}"
    },
    {
      "_class": "curvePoint",
      "cornerRadius": 0,
      "curveFrom": "{0.25751072961373389, 1}",
      "curveMode": 1,
      "curveTo": "{0.25751072961373389, 1}",
      "hasCurveFrom": false,
      "hasCurveTo": false,
      "point": "{0.25751072961373389, 1}"
    },
    {
      "_class": "curvePoint",
      "cornerRadius": 0,
      "curveFrom": "{0, 1}",
      "curveMode": 1,
      "curveTo": "{0, 1}",
      "hasCurveFrom": false,
      "hasCurveTo": false,
      "point": "{0, 1}"
    }
  ],
  "resizingConstraint": 63,
  "resizingType": 0,
  "rotation": 0,
  "shouldBreakMaskChain": false
}