{
  "_class": "symbolInstance",
  "do_objectID": "69451923-0607-4F66-8D8F-6E251BB45F2C",
  "exportOptions": {
    "_class": "exportOptions",
    "exportFormats": [
    ],
    "includedLayerIds": [
    ],
    "layerOptions": 0,
    "shouldTrim": false
  },
  "frame": {
    "_class": "rect",
    "constrainProportions": false,
    "height": 42,
    "width": 258,
    "x": 62,
    "y": 124
  },
  "horizontalSpacing": 0,
  "isFlippedHorizontal": false,
  "isFlippedVertical": false,
  "isLocked": false,
  "isVisible": true,
  "layerListExpandedType": 0,
  "name": "Buttons / Secondary",
  "nameIsFixed": false,
  "originalObjectID": "69451923-0607-4F66-8D8F-6E251BB45F2C",
  "overrideValues": [
    {
      "_class": "overrideValue",
      "do_objectID": "597E7ECE-8DA7-4565-8EE1-6E01B1164AE0",
      "overrideName": "DAFF4E43-9FA6-48FE-9683-993C574D8383_stringValue",
      "value": "Open Settings"
    }
  ],
  "overrides": {
    "DAFF4E43-9FA6-48FE-9683-993C574D8383": "Open Settings"
  },
  "resizingConstraint": 63,
  "resizingType": 0,
  "rotation": 0,
  "scale": 1,
  "shouldBreakMaskChain": false,
  "style": {
    "_class": "style",
    "contextSettings": {
      "_class": "graphicsContextSettings",
      "blendMode": 0,
      "opacity": 0.8
    },
    "endDecorationType": 0,
    "miterLimit": 10,
    "startDecorationType": 0
  },
  "symbolID": "6DBA1753-C6F8-437A-BDF3-AF9D94BC4C73",
  "verticalSpacing": 0
}