{
  "_class": "shapeGroup",
  "clippingMaskMode": 0,
  "do_objectID": "EEDBDF89-5C5C-4D70-AD4E-321E28C70A5B",
  "exportOptions": {
    "_class": "exportOptions",
    "exportFormats": [
    ],
    "includedLayerIds": [
    ],
    "layerOptions": 0,
    "shouldTrim": false
  },
  "frame": {
    "_class": "rect",
    "constrainProportions": false,
    "height": 101.178947368421,
    "width": 93.4736842105263,
    "x": 0.2631578947366506,
    "y": 0
  },
  "hasClickThrough": false,
  "hasClippingMask": false,
  "isFlippedHorizontal": false,
  "isFlippedVertical": false,
  "isLocked": false,
  "isVisible": true,
  "layerListExpandedType": 0,
  "layers": [
    {
      "class": "shapePath",
      "id": "A011CD5E-E947-4272-B30C-798DB0B258C0"
    }
  ],
  "name": "Shape",
  "nameIsFixed": false,
  "originalObjectID": "EEDBDF89-5C5C-4D70-AD4E-321E28C70A5B",
  "resizingConstraint": 63,
  "resizingType": 0,
  "rotation": 0,
  "shouldBreakMaskChain": false,
  "style": {
    "sharedObjectID": "3A2C492E-30E9-4BFB-9158-FA6643B297ED"
  },
  "windingRule": 0
}