{
  "_class": "bitmap",
  "clippingMask": "{{0, 0}, {1, 1}}",
  "do_objectID": "125A75F7-8169-4474-B1C9-6D7580B3684B",
  "exportOptions": {
    "_class": "exportOptions",
    "exportFormats": [
    ],
    "includedLayerIds": [
    ],
    "layerOptions": 0,
    "shouldTrim": false
  },
  "fillReplacesImage": false,
  "frame": {
    "_class": "rect",
    "constrainProportions": true,
    "height": 581,
    "width": 327,
    "x": 24,
    "y": 477
  },
  "image": {
    "_class": "MSJSONFileReference",
    "_ref": "images/25ee8f124b97e9d35f361c7ab38adeaf1caffd15",
    "_ref_class": "MSImageData"
  },
  "isFlippedHorizontal": false,
  "isFlippedVertical": false,
  "isLocked": false,
  "isVisible": true,
  "layerListExpandedType": 0,
  "name": "iOS Settings Wifi",
  "nameIsFixed": false,
  "resizingConstraint": 63,
  "resizingType": 0,
  "rotation": 0,
  "shouldBreakMaskChain": false,
  "style": {
    "_class": "style",
    "contextSettings": {
      "_class": "graphicsContextSettings",
      "blendMode": 15,
      "opacity": 1
    },
    "endDecorationType": 0,
    "miterLimit": 10,
    "startDecorationType": 0
  }
}