{
  "_class": "shapeGroup",
  "clippingMaskMode": 0,
  "do_objectID": "586DFC3A-C70D-4FFF-A6CD-79190FE9A9CA",
  "exportOptions": {
    "_class": "exportOptions",
    "exportFormats": [
    ],
    "includedLayerIds": [
    ],
    "layerOptions": 0,
    "shouldTrim": false
  },
  "frame": {
    "_class": "rect",
    "constrainProportions": false,
    "height": 22.90499999999999,
    "width": 18.94500000000001,
    "x": 91.52999999999999,
    "y": 58.725
  },
  "hasClickThrough": false,
  "hasClippingMask": false,
  "isFlippedHorizontal": false,
  "isFlippedVertical": false,
  "isLocked": false,
  "isVisible": true,
  "layerListExpandedType": 0,
  "layers": [
    {
      "class": "shapePath",
      "id": "417BA51A-1476-45F9-A392-FA459B8A6D61"
    }
  ],
  "name": "Shape",
  "nameIsFixed": false,
  "originalObjectID": "586DFC3A-C70D-4FFF-A6CD-79190FE9A9CA",
  "resizingConstraint": 63,
  "resizingType": 0,
  "rotation": 0,
  "shouldBreakMaskChain": false,
  "style": {
    "_class": "style",
    "endDecorationType": 0,
    "fills": [
      {
        "_class": "fill",
        "color": {
          "_class": "color",
          "alpha": 1,
          "blue": 0.1019607843137255,
          "green": 0.1450980392156863,
          "red": 0.7411764705882353
        },
        "fillType": 0,
        "isEnabled": true,
        "noiseIndex": 0,
        "noiseIntensity": 0,
        "patternFillType": 1,
        "patternTileScale": 1
      }
    ],
    "miterLimit": 10,
    "startDecorationType": 0
  },
  "windingRule": 0
}