{
  "_class": "group",
  "do_objectID": "3B4CF774-5F6D-4301-911A-BD3A835201A8",
  "exportOptions": {
    "_class": "exportOptions",
    "exportFormats": [
    ],
    "includedLayerIds": [
    ],
    "layerOptions": 0,
    "shouldTrim": false
  },
  "frame": {
    "_class": "rect",
    "constrainProportions": false,
    "height": 250,
    "width": 339,
    "x": 18,
    "y": 340
  },
  "hasClickThrough": false,
  "isFlippedHorizontal": false,
  "isFlippedVertical": false,
  "isLocked": false,
  "isVisible": true,
  "layerListExpandedType": 0,
  "layers": [
    {
      "class": "symbolInstance",
      "id": "64C58266-07D4-4138-AB2C-D6FB38241C42"
    },
    {
      "class": "symbolInstance",
      "id": "B5FFB71A-A6EE-4163-A66C-FEACC1E88107"
    },
    {
      "class": "symbolInstance",
      "id": "8428975E-3953-4517-8A0E-DC8BD8B12E55"
    }
  ],
  "name": "Group Copy 2",
  "nameIsFixed": false,
  "resizingConstraint": 63,
  "resizingType": 0,
  "rotation": 0,
  "shouldBreakMaskChain": false,
  "style": {
    "_class": "style",
    "endDecorationType": 0,
    "miterLimit": 10,
    "shadows": [
      {
        "_class": "shadow",
        "blurRadius": 2,
        "color": {
          "_class": "color",
          "alpha": 0.5,
          "blue": 0,
          "green": 0,
          "red": 0
        },
        "contextSettings": {
          "_class": "graphicsContextSettings",
          "blendMode": 0,
          "opacity": 1
        },
        "isEnabled": false,
        "offsetX": 0,
        "offsetY": 1,
        "spread": 0
      }
    ],
    "startDecorationType": 0
  }
}